dtuhpc/__init__.py
dtuhpc/cli/__init__.py
dtuhpc/cli/cli.py
dtuhpc/cli/cli_context.py
dtuhpc/cli/commands/__init__.py
dtuhpc/cli/commands/auth.py
dtuhpc/cli/commands/deploy.py
dtuhpc/cli/commands/exec.py
dtuhpc/cli/commands/init.py
dtuhpc/cli/commands/server/__init__.py
dtuhpc/cli/commands/server/bkill.py
dtuhpc/cli/commands/server/bqueues.py
dtuhpc/cli/commands/server/bstat.py
dtuhpc/cli/commands/server/bsub.py
dtuhpc/cli/commands/server/nodestat.py
dtuhpc/cli/commands/server/showstart.py
dtuhpc/cli/commands/server_command.py
dtuhpc/cli/commands/ssh.py
dtuhpc/commands/__init__.py
dtuhpc/commands/bkill.py
dtuhpc/commands/bqueues.py
dtuhpc/commands/bstat.py
dtuhpc/commands/bsub.py
dtuhpc/commands/command.py
dtuhpc/commands/nodestat.py
dtuhpc/commands/showstart.py
dtuhpc/connector.py
dtuhpc/console.py
dtuhpc/default_jobs/init-pip.toml
dtuhpc/default_jobs/init-poetry.toml
dtuhpc/jobwriter/__init__.py
dtuhpc/jobwriter/commands/__init__.py
dtuhpc/jobwriter/commands/command.py
dtuhpc/jobwriter/commands/load_module_command.py
dtuhpc/jobwriter/job_reader.py
dtuhpc/jobwriter/job_writer.py
dtuhpc/jobwriter/options/__init__.py
dtuhpc/jobwriter/options/core_block_size_option.py
dtuhpc/jobwriter/options/core_ptile_size_option.py
dtuhpc/jobwriter/options/email_for_notifications_option.py
dtuhpc/jobwriter/options/error_output_file_path_option.py
dtuhpc/jobwriter/options/memory_per_core_kill_limit_option.py
dtuhpc/jobwriter/options/memory_per_core_option.py
dtuhpc/jobwriter/options/n_cpu_cores_option.py
dtuhpc/jobwriter/options/name_option.py
dtuhpc/jobwriter/options/option.py
dtuhpc/jobwriter/options/queue_option.py
dtuhpc/jobwriter/options/send_notification_at_end_option.py
dtuhpc/jobwriter/options/send_notification_at_start_option.py
dtuhpc/jobwriter/options/single_host_option.py
dtuhpc/jobwriter/options/standard_output_file_path_option.py
dtuhpc/jobwriter/options/use_gpu_option.py
dtuhpc/jobwriter/options/wall_time_option.py
dtuhpc-2.1.3.dist-info/LICENSE
dtuhpc-2.1.3.dist-info/METADATA
dtuhpc-2.1.3.dist-info/WHEEL
dtuhpc-2.1.3.dist-info/entry_points.txt
dtuhpc-2.1.3.dist-info/RECORD
