Metadata-Version: 2.1
Name: dtuhpc
Version: 2.1.3
Summary: 
Author: Jonas Hoffmannn
Author-email: s204071@student.dtu.dk
Requires-Python: >=3.9,<4.0
Classifier: Programming Language :: Python :: 3
Classifier: Programming Language :: Python :: 3.9
Classifier: Programming Language :: Python :: 3.10
Classifier: Programming Language :: Python :: 3.11
Classifier: Programming Language :: Python :: 3.12
Requires-Dist: cryptography (>=39.0.1,<40.0.0)
Requires-Dist: fabric (>=3.2.2,<4.0.0)
Requires-Dist: gitpython (>=3.1.30,<4.0.0)
Requires-Dist: pygithub (>=1.57,<2.0)
Requires-Dist: python-semantic-release (>=7.33.1,<8.0.0)
Requires-Dist: rich (>=13.2.0,<14.0.0)
Requires-Dist: tomli (>=2.0.1,<3.0.0)
